hyperbolic/__init__.py
hyperbolic/config.py
hyperbolic/logger.py
hyperbolic/magnitudes.py
hyperbolic/plots.py
pz_hyperbolic_temp-0.0.data/scripts/hyp_magnitudes.py
pz_hyperbolic_temp-0.0.data/scripts/hyp_smoothing.py
pz_hyperbolic_temp-0.0.dist-info/LICENSE
pz_hyperbolic_temp-0.0.dist-info/METADATA
pz_hyperbolic_temp-0.0.dist-info/WHEEL
pz_hyperbolic_temp-0.0.dist-info/top_level.txt
pz_hyperbolic_temp-0.0.dist-info/RECORD
