Metadata-Version: 2.1
Name: pz-hyperbolic-temp
Version: 0.0
Summary: Implementation of hyperbolic magnitudes (Lupton et al. 1999).
Home-page: https://github.com/jlvdb/hyperbolic
Author: Jan Luca van den Busch
License-File: LICENSE
Requires-Dist: numpy
Requires-Dist: scipy
Requires-Dist: matplotlib
Requires-Dist: pandas
Requires-Dist: astropandas
